dictnet/__init__.py
dictnet/__main__.py
dictnet/_dictnet.py
dictnet/senset.py
dictnet/util.py
dictnet/cli/__init__.py
dictnet/cli/_util.py
dictnet/cli/download.py
dictnet-0.0.1.dist-info/LICENSE
dictnet-0.0.1.dist-info/METADATA
dictnet-0.0.1.dist-info/WHEEL
dictnet-0.0.1.dist-info/top_level.txt
dictnet-0.0.1.dist-info/RECORD
