Metadata-Version: 2.1
Name: dictnet
Version: 0.0.1
Summary: find similar senses on cambridge dictionary
Home-page: https://github.com/nlpersimon/dictnet
Author: Simon Lee
Author-email: simon2020291@gmail.com
License: UNKNOWN
Platform: UNKNOWN
Classifier: Programming Language :: Python :: 3
Classifier: License :: OSI Approved :: MIT License
Classifier: Operating System :: OS Independent
Requires-Python: >=3.8
License-File: LICENSE
Requires-Dist: gensim (>=3.8.3)
Requires-Dist: wasabi (==0.8.2)
Requires-Dist: typer (==0.4.0)
